[
  {
    "id": "c5524cca-df25-4c8d-bbe8-7352cf32313c",
    "topic_id": "mixed_confidence_independence",
    "title": "Let Them Struggle",
    "subtitle": "Resist the urge to rescue",
    "tips": [
      "Watch them figure it out",
      "Offer encouragement, not solutions",
      "Celebrate the effort, not outcome",
      "Mistakes are learning moments",
      "Building frustration tolerance"
    ],
    "age_groups": [
      "2-4",
      "4-6",
      "6-8",
      "8-10"
    ],
    "emoji": "\ud83d\udcaa",
    "color_theme": "power_gold",
    "source_articles": [],
    "variation": 1,
    "generated_at": "2026-01-26T15:35:17.420067",
    "generation_method": "template"
  },
  {
    "id": "4f865373-615b-497d-b0a4-b83c60a6c18d",
    "topic_id": "mixed_confidence_independence",
    "title": "Age-Appropriate Independence",
    "subtitle": "What they can do themselves",
    "tips": [
      "Toddlers: choose clothes, help clean",
      "Preschool: dress self, simple chores",
      "School-age: homework, morning routine",
      "Tweens: manage schedule, money basics",
      "Gradually increase responsibility"
    ],
    "age_groups": [
      "2-4",
      "4-6",
      "6-8",
      "8-10"
    ],
    "emoji": "\ud83d\udcaa",
    "color_theme": "power_gold",
    "source_articles": [],
    "variation": 2,
    "generated_at": "2026-01-26T15:35:17.420074",
    "generation_method": "template"
  },
  {
    "id": "870c9206-e5c4-41ed-ac94-31e74d5a961d",
    "topic_id": "mixed_confidence_independence",
    "title": "Encourage Risk-Taking",
    "subtitle": "Safe risks build confidence",
    "tips": [
      "Let them climb a bit higher",
      "Support trying new activities",
      "Praise brave attempts",
      "Don't project your fears",
      "Accept minor scrapes and failures"
    ],
    "age_groups": [
      "2-4",
      "4-6",
      "6-8",
      "8-10"
    ],
    "emoji": "\ud83d\udcaa",
    "color_theme": "power_gold",
    "source_articles": [],
    "variation": 3,
    "generated_at": "2026-01-26T15:35:17.420080",
    "generation_method": "template"
  },
  {
    "id": "705a4b71-e1dc-4663-969b-0e3cc3b92f61",
    "topic_id": "mixed_confidence_independence",
    "title": "Growth Mindset Language",
    "subtitle": "Words that build resilience",
    "tips": [
      "Say 'You worked hard' not 'You're smart'",
      "Add 'yet' to 'I can't do it'",
      "Celebrate effort and improvement",
      "Talk about brain growth",
      "Share your own learning struggles"
    ],
    "age_groups": [
      "4-6",
      "6-8",
      "8-10"
    ],
    "emoji": "\ud83d\udcaa",
    "color_theme": "power_gold",
    "source_articles": [],
    "variation": 4,
    "generated_at": "2026-01-26T15:35:17.420085",
    "generation_method": "template"
  },
  {
    "id": "a8007362-6d37-4504-9d63-0dba6e530b19",
    "topic_id": "mixed_confidence_independence",
    "title": "Self-Care Skills",
    "subtitle": "Tending to their own needs",
    "tips": [
      "Teach hand washing, teeth brushing",
      "Practice getting dressed independently",
      "Learn to pour drinks, prepare snacks",
      "Build up to showering alone",
      "Pride comes from doing it themselves"
    ],
    "age_groups": [
      "2-4",
      "4-6",
      "6-8"
    ],
    "emoji": "\ud83d\udcaa",
    "color_theme": "power_gold",
    "source_articles": [],
    "variation": 5,
    "generated_at": "2026-01-26T15:35:17.420090",
    "generation_method": "template"
  },
  {
    "id": "d46106ee-a453-4d40-b426-7edf7883224a",
    "topic_id": "mixed_confidence_independence",
    "title": "Handling Failure",
    "subtitle": "Bounce back after setbacks",
    "tips": [
      "Normalize failure as learning",
      "Share your own failures",
      "Ask 'What would you do differently?'",
      "Focus on what they can control",
      "Help them try again"
    ],
    "age_groups": [
      "4-6",
      "6-8",
      "8-10"
    ],
    "emoji": "\ud83d\udcaa",
    "color_theme": "power_gold",
    "source_articles": [],
    "variation": 6,
    "generated_at": "2026-01-26T15:35:17.420096",
    "generation_method": "template"
  },
  {
    "id": "3019b5ed-705b-4b1a-bcac-15d7e757d89f",
    "topic_id": "mixed_confidence_independence",
    "title": "Building Self-Esteem",
    "subtitle": "Help them feel capable and loved",
    "tips": [
      "Show unconditional love always",
      "Point out their unique strengths",
      "Avoid comparing to others",
      "Listen to their opinions",
      "Let them make choices"
    ],
    "age_groups": [
      "2-4",
      "4-6",
      "6-8",
      "8-10"
    ],
    "emoji": "\ud83d\udcaa",
    "color_theme": "power_gold",
    "source_articles": [],
    "variation": 7,
    "generated_at": "2026-01-26T15:35:17.420101",
    "generation_method": "template"
  },
  {
    "id": "f41393b8-9c76-40ad-9c95-156ffcbbbedc",
    "topic_id": "mixed_confidence_independence",
    "title": "Decision Making Practice",
    "subtitle": "Build judgment through experience",
    "tips": [
      "Start with small decisions",
      "Let them face natural consequences",
      "Talk through decisions together",
      "Respect their choices when safe",
      "Increase stakes as they mature"
    ],
    "age_groups": [
      "4-6",
      "6-8",
      "8-10"
    ],
    "emoji": "\ud83d\udcaa",
    "color_theme": "power_gold",
    "source_articles": [],
    "variation": 8,
    "generated_at": "2026-01-26T15:35:17.420106",
    "generation_method": "template"
  },
  {
    "id": "6fa0725e-01db-48c4-bb4f-7d1898d4b5c2",
    "topic_id": "mixed_confidence_independence",
    "title": "Advocacy Skills",
    "subtitle": "Speaking up for themselves",
    "tips": [
      "Teach 'I need help with...'",
      "Role play asking teachers questions",
      "Let them order at restaurants",
      "Practice polite assertiveness",
      "Step back and let them lead"
    ],
    "age_groups": [
      "4-6",
      "6-8",
      "8-10"
    ],
    "emoji": "\ud83d\udcaa",
    "color_theme": "power_gold",
    "source_articles": [],
    "variation": 9,
    "generated_at": "2026-01-26T15:35:17.420110",
    "generation_method": "template"
  },
  {
    "id": "a3e35dc8-6f8f-4139-b37a-3a2943401ba8",
    "topic_id": "mixed_confidence_independence",
    "title": "Celebrating Uniqueness",
    "subtitle": "Confidence in who they are",
    "tips": [
      "Accept their personality",
      "Don't try to change core traits",
      "Find their interests and support them",
      "Diverse role models matter",
      "They don't need to be like everyone"
    ],
    "age_groups": [
      "2-4",
      "4-6",
      "6-8",
      "8-10"
    ],
    "emoji": "\ud83d\udcaa",
    "color_theme": "power_gold",
    "source_articles": [],
    "variation": 10,
    "generated_at": "2026-01-26T15:35:17.420115",
    "generation_method": "template"
  }
]